AUTHORS
ChangeLog
LICENSE
README.rst
requirements-conda.txt
requirements.txt
setup.cfg
setup.py
test.py
doc/.DS_Store
doc/conf.py
doc/index.rst
doc/api/.DS_Store
doc/api/index.rst
doc/api/graphs/index.rst
doc/api/operators/index.rst
doc/api/operators/pycgsp.linop.conv.rst
doc/api/operators/pycgsp.linop.diff.rst
doc/general/.DS_Store
doc/general/install.rst
doc/images/.DS_Store
doc/images/pycsou.png
doc/notes/index.rst
doc/notes/references.rst
pycgsp/__init__.py
pycgsp/graph.py
pycgsp.egg-info/PKG-INFO
pycgsp.egg-info/SOURCES.txt
pycgsp.egg-info/dependency_links.txt
pycgsp.egg-info/pbr.json
pycgsp.egg-info/requires.txt
pycgsp.egg-info/top_level.txt
pycgsp.egg-info/zip-safe
pycgsp/linop/__init__.py
pycgsp/linop/conv.py
pycgsp/linop/diff.py